reddit_comment_scrapper/__init__.py
reddit_comment_scrapper/main.py
reddit_comment_scrapper-0.3.0.dist-info/entry_points.txt
reddit_comment_scrapper-0.3.0.dist-info/METADATA
reddit_comment_scrapper-0.3.0.dist-info/WHEEL
reddit_comment_scrapper-0.3.0.dist-info/RECORD
