Metadata-Version: 2.1
Name: reddit-comment-scrapper
Version: 0.3.0
Summary: Simple Script for scraping the reddit comment graph
Author: Prarabdha
Author-email: prabodhkumarsrivastav70@gmail.com
Requires-Python: >=3.10,<4.0
Classifier: Programming Language :: Python :: 3
Classifier: Programming Language :: Python :: 3.10
Classifier: Programming Language :: Python :: 3.11
Requires-Dist: praw (>=7.6.1,<8.0.0)
Requires-Dist: typer[all] (>=0.7.0,<0.8.0)
